{
  "title": "Εργασιακή Εμπειρία",
  "contents": [
    {
      "position": "ServiceNow Engineer",
      "company": "Empedus&nbsp;<a href='https://empedus.com/' target='_blank'><i class='fas fa-link'></i></a>",
      "info": [
        {
          "fa" : "<i class='fas fa-cog'></i>",
          "text" : "Σχεδιασμός συστημάτων διοίκησης και υλοποίησή τους εντός της πλατφόρμας του ServiceNow."
        }
      ],
      "date": "Δεκέμβριος 2020 - Σήμερα"
    },
    {
      "position": "Ναυαγοσώστης Ανοιχτής Θαλάσσης",
      "company": "BAYLINE SERVICES",
      "info": [
        {
          "fa" : "<i class='fas fa-water'></i>",
          "text" : "Ναυαγοσώστης Ανοιχτής Θαλάσσης στη Χαλκιδική"
        }
      ],
      "date": "Σεπτέμβριος 2020"
    },
    {
      "position": "Ναυαγοσώστης Πισίνας",
      "company": "Yuppi Camp",
      "info": [
        {
          "fa" : "<i class='fas fa-swimming-pool'></i>",
          "text" : "Ναυαγοσώστης Πισίνας σε παιδική κατασήνωση"
        }
      ],
      "date": "Ιούλιος 2020 - Αύγουστος 2020"
    },
    {
      "position": "Ναυαγοσώστης Ανοιχτής Θαλάσσης",
      "company": "BAYLINE SERVICES",
      "info": [
        {
          "fa" : "<i class='fas fa-water'></i>",
          "text" : "Ναυαγοσώστης Ανοιχτής Θαλάσσης στη Σκιάθο"
        }
      ],
      "date": "Ιούνιος 2019 - Οκτώβριος 2019"
    }
  ]
}